project_vectorizer/__init__.py
project_vectorizer/cli.py
project_vectorizer/core/__init__.py
project_vectorizer/core/config.py
project_vectorizer/core/project.py
project_vectorizer/db/__init__.py
project_vectorizer/db/chromadb_manager.py
project_vectorizer/parsers/__init__.py
project_vectorizer/parsers/code_parser.py
project_vectorizer/utils/__init__.py
project_vectorizer/utils/text_utils.py
project_vectorizer/vector_mcp/__init__.py
project_vectorizer/vector_mcp/server.py
project_vectorizer/vectorizer/__init__.py
project_vectorizer/vectorizer/engine.py
project_vectorizer-0.1.4.dist-info/licenses/LICENSE
project_vectorizer-0.1.4.dist-info/METADATA
project_vectorizer-0.1.4.dist-info/WHEEL
project_vectorizer-0.1.4.dist-info/entry_points.txt
project_vectorizer-0.1.4.dist-info/top_level.txt
project_vectorizer-0.1.4.dist-info/RECORD
