Metadata-Version: 2.4
Name: project-vectorizer
Version: 0.1.4
Summary: CLI tool for vectorizing codebases and serving them via MCP
Author-email: StarkBak <bak.stark06@gmail.com>
License: MIT
Project-URL: Homepage, https://github.com/starkbaknet/project-vectorizer
Project-URL: Documentation, https://github.com/starkbaknet/project-vectorizer#readme
Project-URL: Repository, https://github.com/starkbaknet/project-vectorizer
Project-URL: Issues, https://github.com/starkbaknet/project-vectorizer/issues
Project-URL: Changelog, https://github.com/starkbaknet/project-vectorizer/releases
Keywords: vectorization,code-search,embeddings,semantic-search,mcp,chromadb,codebase-analysis,ai-tools
Classifier: Development Status :: 4 - Beta
Classifier: Intended Audience :: Developers
Classifier: License :: OSI Approved :: MIT License
Classifier: Programming Language :: Python :: 3
Classifier: Programming Language :: Python :: 3.9
Classifier: Programming Language :: Python :: 3.10
Classifier: Programming Language :: Python :: 3.11
Classifier: Programming Language :: Python :: 3.12
Classifier: Topic :: Software Development :: Libraries :: Python Modules
Classifier: Topic :: Software Development :: Code Generators
Classifier: Topic :: Text Processing :: Indexing
Classifier: Operating System :: OS Independent
Requires-Python: >=3.9
License-File: LICENSE
Requires-Dist: click>=8.0.0
Requires-Dist: numpy>=1.24.0
Requires-Dist: sentence-transformers>=2.2.0
Requires-Dist: openai>=1.0.0
Requires-Dist: gitpython>=3.1.0
Requires-Dist: watchdog>=3.0.0
Requires-Dist: pydantic>=2.0.0
Requires-Dist: rich>=13.0.0
Requires-Dist: mcp>=1.0.0
Requires-Dist: aiohttp>=3.8.0
Requires-Dist: tree-sitter>=0.20.0
Requires-Dist: tree-sitter-python>=0.20.0
Requires-Dist: tree-sitter-javascript>=0.20.0
Requires-Dist: tree-sitter-typescript>=0.20.0
Requires-Dist: tree-sitter-go>=0.20.0
Requires-Dist: tree-sitter-rust>=0.20.0
Requires-Dist: tree-sitter-java>=0.20.0
Requires-Dist: tiktoken>=0.5.0
Requires-Dist: python-dotenv>=1.0.0
Requires-Dist: chromadb>=0.4.0
Requires-Dist: psutil>=5.9.0
Provides-Extra: dev
Requires-Dist: pytest>=7.0.0; extra == "dev"
Requires-Dist: pytest-asyncio>=0.21.0; extra == "dev"
Requires-Dist: pytest-cov>=4.0.0; extra == "dev"
Requires-Dist: pytest-timeout>=2.1.0; extra == "dev"
Requires-Dist: black>=23.0.0; extra == "dev"
Requires-Dist: isort>=5.12.0; extra == "dev"
Requires-Dist: mypy>=1.0.0; extra == "dev"
Requires-Dist: flake8>=6.0.0; extra == "dev"
Dynamic: license-file
